odoo9_addon_website_no_crawler-9.0.1.0.0.99.dev2-py2.7-nspkg.pth
odoo9_addon_website_no_crawler-9.0.1.0.0.99.dev2.dist-info/DESCRIPTION.rst
odoo9_addon_website_no_crawler-9.0.1.0.0.99.dev2.dist-info/METADATA
odoo9_addon_website_no_crawler-9.0.1.0.0.99.dev2.dist-info/RECORD
odoo9_addon_website_no_crawler-9.0.1.0.0.99.dev2.dist-info/WHEEL
odoo9_addon_website_no_crawler-9.0.1.0.0.99.dev2.dist-info/metadata.json
odoo9_addon_website_no_crawler-9.0.1.0.0.99.dev2.dist-info/namespace_packages.txt
odoo9_addon_website_no_crawler-9.0.1.0.0.99.dev2.dist-info/top_level.txt
odoo_addons/website_no_crawler/README.rst
odoo_addons/website_no_crawler/__init__.py
odoo_addons/website_no_crawler/__openerp__.py
odoo_addons/website_no_crawler/i18n/website_no_crawler.pot
odoo_addons/website_no_crawler/static/description/icon.png
odoo_addons/website_no_crawler/views/disable_robots.xml
