Metadata-Version: 2.0
Name: odoo9-addon-website-no-crawler
Version: 9.0.1.0.0.99.dev2
Summary: Disables robots.txt for indexing by webcrawlers like Google
Home-page: UNKNOWN
Author: B-Informed B.V.,Odoo Community Association (OCA)
Author-email: support@odoo-community.org
License: AGPL-3
Platform: UNKNOWN
Classifier: Programming Language :: Python
Classifier: Framework :: Odoo
Classifier: License :: OSI Approved :: GNU Affero General Public License v3
Requires-Python: ~=2.7
Requires-Dist: odoo (<9.1a,>=9.0a)
